pysid/__init__.py
pysid/correlation/__init__.py
pysid/correlation/autocorr.py
pysid/correlation/croscorr.py
pysid/identification/__init__.py
pysid/identification/accr.py
pysid/identification/comcrit.py
pysid/identification/ivmethod.py
pysid/identification/models.py
pysid/identification/pemethod.py
pysid/identification/recursive.py
pysid/identification/solvers.py
pysid/identification/tseries.py
pysid/io/__init__.py
pysid/io/check.py
pysid/io/csv_data.py
pysid/io/print.py
pysid/tests/__init__.py
pysid/tests/pem tests.py
pysid-0.1.1.dist-info/LICENSE
pysid-0.1.1.dist-info/METADATA
pysid-0.1.1.dist-info/WHEEL
pysid-0.1.1.dist-info/top_level.txt
pysid-0.1.1.dist-info/RECORD
