Metadata-Version: 2.1
Name: pysid
Version: 0.1.1
Summary: System Identification tools for python
Home-page: https://github.com/edumapurunga/pysid
Author: Eduardo Mapurunga
Author-email: edumapurunga@gmail.com
License: UNKNOWN
Platform: UNKNOWN
Classifier: Programming Language :: Python :: 3
Classifier: License :: OSI Approved :: MIT License
Classifier: Operating System :: OS Independent
Requires-Python: >=3.6
License-File: LICENSE
Requires-Dist: numpy (>=1.19)
Requires-Dist: scipy (>=1.4)
